__init__.py
caat.py
caat-0.2.1.dist-info/LICENSE
caat-0.2.1.dist-info/METADATA
caat-0.2.1.dist-info/WHEEL
caat-0.2.1.dist-info/top_level.txt
caat-0.2.1.dist-info/RECORD
