Metadata-Version: 2.1
Name: caat
Version: 0.2.1
Summary: CAAT: Commands as Arrow Types, a FFI that works across languages.
Author-email: Alec Davis <alecdavis@killerrabbit.xyz>
Project-URL: Homepage, https://github.com/Ki11erRabbit/caat_python
Project-URL: Issues, https://github.com/Ki11erRabbit/caat_python/issues
Classifier: Programming Language :: Python :: 3
Classifier: License :: OSI Approved :: MIT License
Classifier: Operating System :: Unix
Requires-Python: >3.6
License-File: LICENSE
